pyair-3.0.0.dist-info/RECORD
pyair-3.0.0.dist-info/WHEEL
pyair-3.0.0.dist-info/top_level.txt
pyair-3.0.0.dist-info/METADATA
pyair-3.0.0.dist-info/DESCRIPTION.rst
pyair-3.0.0.dist-info/metadata.json
pyair/xair.py
pyair/stats.py
pyair/date.py
pyair/reg.py
pyair/__init__.py
