Metadata-Version: 2.0
Name: pyair
Version: 3.0.0
Summary: For working with French air quality data and the Iseo XAIR database
Home-page: https://github.com/LionelR/pyair
Author: Lionel Roubeyrie
Author-email: lroubeyrie@limair.asso.fr
License: BSD
Keywords: air quality xair iseo french reglementation statistics
Platform: UNKNOWN
Requires-Dist: pandas
Requires-Dist: cx-oracle
